django_dropbox_upload_handler/__init__.py
django_dropbox_upload_handler/handler.py
django_dropbox_upload_handler/urls.py
django_dropbox_upload_handler/views.py
django_dropbox_upload_handler-0.1.1.dist-info/DESCRIPTION.rst
django_dropbox_upload_handler-0.1.1.dist-info/METADATA
django_dropbox_upload_handler-0.1.1.dist-info/RECORD
django_dropbox_upload_handler-0.1.1.dist-info/WHEEL
django_dropbox_upload_handler-0.1.1.dist-info/metadata.json
django_dropbox_upload_handler-0.1.1.dist-info/top_level.txt
