Metadata-Version: 2.0
Name: django-dropbox-upload-handler
Version: 0.1.1
Summary: Transfer Uploaded Files to Dropbox
Home-page: https://github.com/jagonalez/django-dropbox-upload-handler
Author: Jeremy Gonzalez
Author-email: jeremy@jeremyg.net
License: MIT
Keywords: django-dropbox-upload-handler
Platform: UNKNOWN
Classifier: Development Status :: 3 - Alpha
Classifier: Framework :: Django
Classifier: Framework :: Django :: 1.8
Classifier: Framework :: Django :: 1.9
Classifier: Framework :: Django :: 1.10
Classifier: Intended Audience :: Developers
Classifier: License :: OSI Approved :: BSD License
Classifier: Natural Language :: English
Classifier: Programming Language :: Python :: 2
Classifier: Programming Language :: Python :: 2.7
Classifier: Programming Language :: Python :: 3
Classifier: Programming Language :: Python :: 3.3
Classifier: Programming Language :: Python :: 3.4
Classifier: Programming Language :: Python :: 3.5
